pygame_colors/__init__.py
pygame_colors/pygame_colors.py
pygame_colors-1.0.0.dist-info/LICENCE.txt
pygame_colors-1.0.0.dist-info/METADATA
pygame_colors-1.0.0.dist-info/WHEEL
pygame_colors-1.0.0.dist-info/top_level.txt
pygame_colors-1.0.0.dist-info/RECORD
