Metadata-Version: 2.1
Name: pygame_colors
Version: 1.0.0
Summary: A simple Pygame module for accessing predefined colors that will ease your scripting and save the time
Home-page: https://github.com/basitganie/pygame_colors
Author: Basit Ahmad Ganie
Author-email: basitahmed1412@gmail.com
License: MIT
Classifier: Programming Language :: Python :: 3
Classifier: License :: OSI Approved :: MIT License
Classifier: Operating System :: OS Independent
Requires-Python: >=3.6
License-File: LICENCE.txt
Requires-Dist: pygame
